pytrendsplus/__init__.py
pytrendsplus/prediction.py
pytrendsplus/pytrendsplus.py
pytrendsplus/suggestions.py
pytrendsplus/visualization.py
pytrendsplus-0.1.0.dist-info/METADATA
pytrendsplus-0.1.0.dist-info/WHEEL
pytrendsplus-0.1.0.dist-info/top_level.txt
pytrendsplus-0.1.0.dist-info/RECORD
