Metadata-Version: 2.1
Name: pytrendsplus
Version: 0.1.0
Summary: A Python library to fetch and analyze Google Trends data with additional functionalities.
Home-page: https://github.com/kaneda2004/pytrendsplus
Classifier: Development Status :: 3 - Alpha
Classifier: Intended Audience :: Developers
Classifier: License :: OSI Approved :: MIT License
Classifier: Programming Language :: Python :: 3
Classifier: Programming Language :: Python :: 3.6
Classifier: Programming Language :: Python :: 3.7
Classifier: Programming Language :: Python :: 3.8
Classifier: Programming Language :: Python :: 3.9
Requires-Python: >=3.6
Requires-Dist: pytrends
Requires-Dist: matplotlib
Requires-Dist: pandas
Requires-Dist: scikit-learn
Requires-Dist: selenium
Requires-Dist: numpy
